{
  "kind": "collectionType",
  "collectionName": "kenyas",
  "info": {
    "singularName": "kenya",
    "pluralName": "kenyas",
    "displayName": "Kenya"
  },
  "options": {
    "draftAndPublish": true
  },
  "pluginOptions": {},
  "attributes": {
    "name": {
      "type": "string"
    },
    "cost": {
      "type": "integer"
    },
    "shortDescription": {
      "type": "text"
    },
    "longDescription": {
      "type": "text"
    },
    "mainImage": {
      "allowedTypes": [
        "images",
        "files",
        "videos",
        "audios"
      ],
      "type": "media",
      "multiple": false
    }
  }
}
